<?xml version="1.0" ?>
	<institution>
		<professor>
			<name>Meysam Asgari</name>
			<title>Assistant Professor</title>
			<office>Gaines Hall, Room 17</office>
			<email>asgari@ohsu.edu</email>
			<phone>503 346-3751</phone>
			<website>http://cslu.ohsu.edu/~asgari/<website>
			<image>http://www.ohsu.edu/xd/research/centers-institutes/center-for-spoken-language-understanding/images/meysam-resized.jpg<\image>
		</professor>
		<professor>
			<name>Steven Bedrick</name>
			<title>Assistant Professor </title>
			<office>Gaines Hall, Room 19</office>
			<email>bedricks@ohsu.edu</email>
			<phone>503 346-3750</phone>
			<website>http://www.bedrick.org/<website>
			<image>http://www.ohsu.edu/xd/research/centers-institutes/center-for-spoken-language-understanding/images/Steven-mirror.jpg<\image>
		</professor>
		<professor>
			<name>Peter Heeman</name>
			<title>Program Director, CSE and EE Research Associate Professor </title>
			<office>Gaines Hall, Room 40AA</office>
			<email>heemanp@ohsu.edu</email>
			<phone>503 346-3755</phone>
			<website>http://cslu.ohsu.edu/~heeman/<website>
			<image>http://www.ohsu.edu/xd/education/schools/school-of-medicine/departments/basic-science-departments/csee/csee-people/images/heeman_peter.jpg<\image>
		</professor>
		<professor>
			<name>Alexander Kain</name>
			<title>Associate Professor</title>
			<office>Gaines Hall Room 15</office>
			<email>kaina@ohsu.edu</email>
			<phone>503 346-3757</phone>
			<website>http://cslu.ohsu.edu/~kain/<website>
			<image>http://www.ohsu.edu/xd/research/centers-institutes/center-for-spoken-language-understanding/images/alexanderkain120x150_1.jpg<\image>
		</professor>
		<professor>
			<name>Alison Hill</name>
			<title>Assistant Professor </title>
			<office>Gaines Hall, Room 21</office>
			<email>hillali@ohsu.edu</email>
			<phone>503 346-3756</phone>
			<website>http://www.ohsu.edu/xd/education/schools/school-of-medicine/departments/basic-science-departments/csee/csee-people/hill.cfm<website>
			<image>http://www.ohsu.edu/xd/research/centers-institutes/center-for-spoken-language-understanding/images/presmanes-hill-120x150-v-2.jpg<\image>
		</professor>
		<professor>
			<name>Xubo Song</name>
			<title>Professor</title>
			<office>Gaines Hall, Room 114</office>
			<email>songx@ohsu.edu</email>
			<phone>503 346-3762</phone>
			<website>http://cslu.ohsu.edu/~xubosong<website>
			<image>http://www.ohsu.edu/xd/research/centers-institutes/center-for-spoken-language-understanding/images/XuboSong2015-001.jpg<\image>
		</professor>
		<professor>
			<name>Kemal Sonmez</name>
			<title>Associate Professor </title>
			<office>Gaines Hall, Room 118</office>
			<email>sonmezk@ohsu.edu</email>
			<phone>503 346-3763</phone>
			<website>http://www.ohsu.edu/xd/education/schools/school-of-medicine/departments/basic-science-departments/csee/csee-people/sonmez.cfm<website>
			<image>http://www.ohsu.edu/xd/research/centers-institutes/center-for-spoken-language-understanding/images/sonmez.jpg<\image>
		</professor>
		<professor>
			<name>Jan van Santen</name>
			<title>Professor Director, Center for Spoken Language Understanding</title>
			<office>Gaines Hall, Room 102</office>
			<email>vansantj@ohsu.edu</email>
			<phone>503 346-3765</phone>
			<website>http://cslu.ohsu.edu/~vansanten<website>
			<image>http://www.ohsu.edu/xd/research/centers-institutes/center-for-spoken-language-understanding/images/vansanten-2_1.jpg<\image>
		</professor>
		<professor>
			<name>Stephen Wu</name>
			<title>Assistant Professor</title>
			<office>Gaines Hall, Room 110</office>
			<email>wst@ohsu.edu</email>
			<phone></phone>
			<website>https://sites.google.com/site/stephentzeinnwu/<website>
			<image>http://www.ohsu.edu/xd/research/centers-institutes/center-for-spoken-language-understanding/images/Wu_Stephen_120x150.jpg<\image>
		</professor>
	</institution>
