<?xml version="1.0" ?>
	<institution>
		<professor>
			<name>Charles W. Anderson</name>
			<papers>15.4333333333</papers>
		</professor>
		<professor>
			<name>Asa Ben-Hur</name>
			<papers>21.4916666667</papers>
		</professor>
		<professor>
			<name>J. Ross Beveridge</name>
			<papers>43.95</papers>
		</professor>
		<professor>
			<name>James M. Bieman</name>
			<papers>78.7</papers>
		</professor>
		<professor>
			<name>A. P. Willem Bohm</name>
			<papers>-1</papers>
		</professor>
		<professor>
			<name>Christina Boucher</name>
			<papers>24.6666666667</papers>
		</professor>
		<professor>
			<name>Hamid Reza Chitsaz</name>
			<papers>7.575</papers>
		</professor>
		<professor>
			<name>Bruce Draper</name>
			<papers>49.575</papers>
		</professor>
		<professor>
			<name>Sudipto Ghosh</name>
			<papers>36.6595238095</papers>
		</professor>
		<professor>
			<name>Adele E. Howe</name>
			<papers>49.3916666667</papers>
		</professor>
		<professor>
			<name>Yashwant K. Malaiya</name>
			<papers>46.1666666667</papers>
		</professor>
		<professor>
			<name>Daniel F. Massey</name>
			<papers>-1</papers>
		</professor>
		<professor>
			<name>Ross M. McConnell</name>
			<papers>32.25</papers>
		</professor>
		<professor>
			<name>Cathie Olschanowsky</name>
			<papers>-1</papers>
		</professor>
		<professor>
			<name>Sangmi Lee Pallickara</name>
			<papers>17.0194444444</papers>
		</professor>
		<professor>
			<name>Christos Papadopoulos</name>
			<papers>27.8206349206</papers>
		</professor>
		<professor>
			<name>Sanjay Rajopadhye</name>
			<papers>0</papers>
		</professor>
		<professor>
			<name>Indrajit Ray</name>
			<papers>60.244047619</papers>
		</professor>
		<professor>
			<name>Indrakshi Ray</name>
			<papers>76.1111111111</papers>
		</professor>
		<professor>
			<name>Jaime Ruiz</name>
			<papers>13.7833333333</papers>
		</professor>
		<professor>
			<name>L. Darrell Whitley</name>
			<papers>60.3928571429</papers>
		</professor>
		<professor>
			<name>Chris Wilcox</name>
			<papers>5.33333333333</papers>
		</professor>
		<professor>
			<name>Anura P. Jayasumana</name>
			<papers>65.5166666667</papers>
		</professor>
		<professor>
			<name>Michael Kirby</name>
			<papers>6.75</papers>
		</professor>
		<professor>
			<name>H. J. Siegel</name>
			<papers>126.172619048</papers>
		</professor>
		<professor>
			<name>Jack Applin&lt;/a&gt;</name>
			<papers>-1</papers>
		</professor>
		<professor>
			<name>Joe Gersch</name>
			<papers>2.0</papers>
		</professor>
		<professor>
			<name>Elaine Regelson</name>
			<papers>1.0</papers>
		</professor>
		<professor>
			<name>Geri Georg</name>
			<papers>24.8583333333</papers>
		</professor>
		<professor>
			<name>Lisa Knebl</name>
			<papers>-1</papers>
		</professor>
		<professor>
			<name>James L. Peterson</name>
			<papers>18.6333333333</papers>
		</professor>
		<professor>
			<name>Wayne Trzyn</name>
			<papers>-1</papers>
		</professor>
	</institution>
