<?xml version="1.0" ?>
	<institution>
		<professor>
			<name>Daniel Ahn</name>
			<papers>-1</papers>
		</professor>
		<professor>
			<name>Karen J. Bigrigg</name>
			<papers>-1</papers>
		</professor>
		<professor>
			<name>Michael W. Bigrigg</name>
			<papers>4.94444444444</papers>
		</professor>
		<professor>
			<name>Jarrett F. Billingsley</name>
			<papers>-1</papers>
		</professor>
		<professor>
			<name>Donald M. Bonidie</name>
			<papers>-1</papers>
		</professor>
		<professor>
			<name>Matthew Bowytz</name>
			<papers>-1</papers>
		</professor>
		<professor>
			<name>Bruce G. Buchanan</name>
			<papers>49.503968254</papers>
		</professor>
		<professor>
			<name>Shi-Kuo Chang</name>
			<papers>181.533333333</papers>
		</professor>
		<professor>
			<name>Donald M. Chiarulli</name>
			<papers>20.9023809524</papers>
		</professor>
		<professor>
			<name>Bruce R. Childers</name>
			<papers>52.2928571429</papers>
		</professor>
		<professor>
			<name>Panos Chrysanthis</name>
			<papers>86.0</papers>
		</professor>
		<professor>
			<name>Henry Chuang</name>
			<papers>15.0</papers>
		</professor>
		<professor>
			<name>Michael Costantino</name>
			<papers>0.825</papers>
		</professor>
		<professor>
			<name>Paul Covaleski</name>
			<papers>-1</papers>
		</professor>
		<professor>
			<name>Mike Devine</name>
			<papers>1.0</papers>
		</professor>
		<professor>
			<name>Nicholas L. Farnan</name>
			<papers>6.16666666667</papers>
		</professor>
		<professor>
			<name>Paulo B. Ferreira</name>
			<papers>-1</papers>
		</professor>
		<professor>
			<name>John Franolich</name>
			<papers>-1</papers>
		</professor>
		<professor>
			<name>William C. Garrison</name>
			<papers>7.83333333333</papers>
		</professor>
		<professor>
			<name>Milos Hauskrecht</name>
			<papers>52.3833333333</papers>
		</professor>
		<professor>
			<name>Timothy L. Hoffman</name>
			<papers>-1</papers>
		</professor>
		<professor>
			<name>Rebecca Hwa</name>
			<papers>17.9083333333</papers>
		</professor>
		<professor>
			<name>Thumrongsak Kosiyatrakul</name>
			<papers>2.0</papers>
		</professor>
		<professor>
			<name>Adriana I. Kovashka</name>
			<papers>-1</papers>
		</professor>
		<professor>
			<name>David Krebs</name>
			<papers>1.83333333333</papers>
		</professor>
		<professor>
			<name>William J. Laboon</name>
			<papers>-1</papers>
		</professor>
		<professor>
			<name>Alexandros Labrinidis</name>
			<papers>41.6119047619</papers>
		</professor>
		<professor>
			<name>John R. Lange</name>
			<papers>17.0333333333</papers>
		</professor>
		<professor>
			<name>Adam J. Lee</name>
			<papers>43.65</papers>
		</professor>
		<professor>
			<name>Michael C. Lipschultz</name>
			<papers>-1</papers>
		</professor>
		<professor>
			<name>Diane J. Litman</name>
			<papers>94.8142857143</papers>
		</professor>
		<professor>
			<name>Rami Melhem</name>
			<papers>115.3</papers>
		</professor>
		<professor>
			<name>Bryan N. Mills</name>
			<papers>6.0</papers>
		</professor>
		<professor>
			<name>Jonathan R. Misurda</name>
			<papers>-1</papers>
		</professor>
		<professor>
			<name>Daniel Mosse</name>
			<papers>70.9393217893</papers>
		</professor>
		<professor>
			<name>George A. Novacky</name>
			<papers>0.5</papers>
		</professor>
		<professor>
			<name>Jason Prodonovich</name>
			<papers>-1</papers>
		</professor>
		<professor>
			<name>Kirk R. Pruhs</name>
			<papers>-1</papers>
		</professor>
		<professor>
			<name>Patricia T. Quirin</name>
			<papers>-1</papers>
		</professor>
		<professor>
			<name>John C. Ramirez</name>
			<papers>3.0</papers>
		</professor>
		<professor>
			<name>Mohamed A. Sharaf</name>
			<papers>31.1928571429</papers>
		</professor>
		<professor>
			<name>Siegfried Treu</name>
			<papers>9.58333333333</papers>
		</professor>
		<professor>
			<name>Daniel E. Walker</name>
			<papers>-1</papers>
		</professor>
		<professor>
			<name>Jingtao Wang</name>
			<papers>16.0</papers>
		</professor>
		<professor>
			<name>Jeffrey P. Wheeler</name>
			<papers>-1</papers>
		</professor>
		<professor>
			<name>Janyce M. Wiebe</name>
			<papers>-1</papers>
		</professor>
		<professor>
			<name>Youtao Zhang</name>
			<papers>50.8166666667</papers>
		</professor>
		<professor>
			<name>Taieb Znati</name>
			<papers>85.1194444444</papers>
		</professor>
	</institution>
